nhlscrapi/__init__.py
nhlscrapi/_tools.py
nhlscrapi/constants.py
nhlscrapi/games/__init__.py
nhlscrapi/games/cumstats.py
nhlscrapi/games/events.py
nhlscrapi/games/eventsummary.py
nhlscrapi/games/faceoffcomp.py
nhlscrapi/games/game.py
nhlscrapi/games/gamesummary.py
nhlscrapi/games/playbyplay.py
nhlscrapi/games/repscrwrap.py
nhlscrapi/games/rosters.py
nhlscrapi/games/toi.py
nhlscrapi/scrapr/__init__.py
nhlscrapi/scrapr/descparser.py
nhlscrapi/scrapr/eventparser.py
nhlscrapi/scrapr/eventsummrep.py
nhlscrapi/scrapr/faceoffrep.py
nhlscrapi/scrapr/gamesummrep.py
nhlscrapi/scrapr/nhlreq.py
nhlscrapi/scrapr/officialsparser.py
nhlscrapi/scrapr/reportloader.py
nhlscrapi/scrapr/rosterrep.py
nhlscrapi/scrapr/rtss.py
nhlscrapi/scrapr/shootoutrep.py
nhlscrapi/scrapr/shotsummrep.py
nhlscrapi/scrapr/teamnameparser.py
nhlscrapi/scrapr/toirep.py
nhlscrapi-0.4.4.data/scripts/gamedata.py
nhlscrapi-0.4.4.dist-info/METADATA
nhlscrapi-0.4.4.dist-info/RECORD
nhlscrapi-0.4.4.dist-info/WHEEL
nhlscrapi-0.4.4.dist-info/top_level.txt
tests/__init__.py
tests/test_eventsumm.py
tests/test_faceoffcomp.py
tests/test_rtss.py
tests/test_toishiftsummary.py
