Metadata-Version: 2.1
Name: nhlscrapi
Version: 0.4.4
Summary: NHL Scrapr API for Python
Home-page: https://github.com/robhowley/nhlscrapi
Author: Rob Howley
Author-email: howley.robert@gmail.com
License: Apache Software License version 2.0
Keywords: nhlscrapi
Platform: any
Classifier: Development Status :: 2 - Pre-Alpha
Classifier: Intended Audience :: Developers
Classifier: License :: OSI Approved :: BSD License
Classifier: Natural Language :: English
Classifier: Programming Language :: Python :: 2.7
Classifier: Programming Language :: Python :: 3
Classifier: Programming Language :: Python :: 3.3
Classifier: Operating System :: OS Independent
Classifier: Topic :: Software Development :: Libraries :: Python Modules
Requires-Dist: lxml
Requires-Dist: requests
